{
  "tests": [
    {
      "name": "test_add",
      "setup": "sudo -H pip3 install -r requirements.txt",
      "run": "pytest -v  -k \"test_add\"",
      "input": "",
      "output": "",
      "comparison": "included",
      "timeout": 10,
      "points": 1
    },
    {
      "name": "test_subtract",
      "setup": "sudo -H pip3 install -r requirements.txt",
      "run": "pytest -v  -k \"test_subtract\"",
      "input": "",
      "output": "",
      "comparison": "included",
      "timeout": 10,
      "points": 1
    },
    {
      "name": "test_multiply",
      "setup": "sudo -H pip3 install -r requirements.txt",
      "run": "pytest -v  -k \"test_multiply\"",
      "input": "",
      "output": "",
      "comparison": "included",
      "timeout": 10,
      "points": 1
    },
    {
      "name": "test_divide",
      "setup": "sudo -H pip3 install -r requirements.txt",
      "run": "pytest -v  -k \"test_divide\"",
      "input": "",
      "output": "",
      "comparison": "included",
      "timeout": 10,
      "points": 1
    }
  ]
}